vishnuoperators/Comparisonop.py
vishnuoperators/__init__.py
vishnuoperators/module1.py
vishnuoperators/module2.py
vishnuoperators/module3.py
vishnuoperators/module4.py
vishnuoperators/module5.py
vishnuoperators/module6.py
vishnuoperators/module7.py
vishnuoperators/module8.py
vishnuoperators-0.2.dist-info/LICENSE
vishnuoperators-0.2.dist-info/METADATA
vishnuoperators-0.2.dist-info/WHEEL
vishnuoperators-0.2.dist-info/top_level.txt
vishnuoperators-0.2.dist-info/RECORD
