Metadata-Version: 2.1
Name: vishnuoperators
Version: 0.2
Summary: A simple Python package for basic arithmetic operations and 
Home-page: https://github.com/yourusername/vishnuoperators
Author: Vishnu
Author-email: bvv@gmail.com
License: MIT
Requires-Python: >=3.6
License-File: LICENSE
